[
	{
		"id" : 232,
		"challanNumber" : "216192",
		"studentId" : 1,
		"feeStructureId" : null,
		"amount" : 16666,
		"paidAmount" : 0,
		"totalAmount" : 16666,
		"remainingAmount" : 16666,
		"discount" : 0,
		"fineAmount" : 0,
		"lateFeeFine" : 0,
		"settledAmount" : 16666,
		"dueDate" : "2026-04-27",
		"issueDate" : "2026-04-27 18:14:30.871",
		"paidDate" : null,
		"status" : "VOID",
		"installmentNumber" : 1,
		"coveredInstallments" : "1",
		"selectedHeads" : "[]",
		"paymentHistory" : "[]",
		"remarks" : "Challan for 2026-04; Superseded by Challan #130407 (May 2025-2026); Fully settled via Challan #957430 (November 2025-2026)",
		"challanType" : "INSTALLMENT",
		"studentArrearId" : null,
		"studentClassId" : 1,
		"studentProgramId" : 1,
		"studentSectionId" : null,
		"studentFeeInstallmentId" : 1,
		"month" : "April",
		"session" : "2025-2026",
		"sessionId" : 1,
		"supersededById" : 233,
		"createdAt" : "2026-04-27 18:14:30.871",
		"updatedAt" : "2026-04-27 18:18:24.649",
		"isLocked" : 1,
		"settlementSnapshot" : "null"
	},
	{
		"id" : 233,
		"challanNumber" : "130407",
		"studentId" : 1,
		"feeStructureId" : null,
		"amount" : 16666,
		"paidAmount" : 0,
		"totalAmount" : 16666,
		"remainingAmount" : 16666,
		"discount" : 0,
		"fineAmount" : 0,
		"lateFeeFine" : 0,
		"settledAmount" : 13334,
		"dueDate" : "2026-05-27",
		"issueDate" : "2026-04-27 18:14:37.455",
		"paidDate" : null,
		"status" : "VOID",
		"installmentNumber" : 2,
		"coveredInstallments" : "2",
		"selectedHeads" : "[]",
		"paymentHistory" : "[]",
		"remarks" : "Challan for 2026-05; Superseded by Challan #951401 (June 2025-2026); Partially settled (PKR 13,334 / 16,666) via Challan #957430",
		"challanType" : "INSTALLMENT",
		"studentArrearId" : null,
		"studentClassId" : 1,
		"studentProgramId" : 1,
		"studentSectionId" : null,
		"studentFeeInstallmentId" : 2,
		"month" : "May",
		"session" : "2025-2026",
		"sessionId" : 1,
		"supersededById" : 234,
		"createdAt" : "2026-04-27 18:14:37.455",
		"updatedAt" : "2026-04-27 18:18:24.649",
		"isLocked" : 1,
		"settlementSnapshot" : "null"
	},
	{
		"id" : 234,
		"challanNumber" : "951401",
		"studentId" : 1,
		"feeStructureId" : null,
		"amount" : 16666,
		"paidAmount" : 0,
		"totalAmount" : 16666,
		"remainingAmount" : 16666,
		"discount" : 0,
		"fineAmount" : 0,
		"lateFeeFine" : 0,
		"settledAmount" : 0,
		"dueDate" : "2026-06-27",
		"issueDate" : "2026-04-27 18:14:42.061",
		"paidDate" : null,
		"status" : "VOID",
		"installmentNumber" : 3,
		"coveredInstallments" : "3",
		"selectedHeads" : "[]",
		"paymentHistory" : "[]",
		"remarks" : "Challan for 2026-06; Superseded by Challan #957430 (November 2025-2026)",
		"challanType" : "INSTALLMENT",
		"studentArrearId" : null,
		"studentClassId" : 1,
		"studentProgramId" : 1,
		"studentSectionId" : null,
		"studentFeeInstallmentId" : 3,
		"month" : "June",
		"session" : "2025-2026",
		"sessionId" : 1,
		"supersededById" : 235,
		"createdAt" : "2026-04-27 18:14:42.061",
		"updatedAt" : "2026-04-27 18:14:54.117",
		"isLocked" : 0,
		"settlementSnapshot" : "null"
	},
	{
		"id" : 235,
		"challanNumber" : "957430",
		"studentId" : 1,
		"feeStructureId" : null,
		"amount" : 16666,
		"paidAmount" : 30000,
		"totalAmount" : 16666,
		"remainingAmount" : 36664,
		"discount" : 0,
		"fineAmount" : 0,
		"lateFeeFine" : 0,
		"settledAmount" : 0,
		"dueDate" : "2026-11-27",
		"issueDate" : "2026-04-27 18:14:54.096",
		"paidDate" : "2026-04-27",
		"status" : "PARTIAL",
		"installmentNumber" : 4,
		"coveredInstallments" : "1-4",
		"selectedHeads" : "[]",
		"paymentHistory" : "[{\"date\": \"2026-04-27T00:00:00.000Z\", \"amount\": 30000, \"method\": \"Cash\", \"remarks\": \"Challan for 2026-11\", \"discount\": 0}]",
		"remarks" : "Challan for 2026-11",
		"challanType" : "INSTALLMENT",
		"studentArrearId" : null,
		"studentClassId" : 1,
		"studentProgramId" : 1,
		"studentSectionId" : null,
		"studentFeeInstallmentId" : 4,
		"month" : "November",
		"session" : "2025-2026",
		"sessionId" : 1,
		"supersededById" : null,
		"createdAt" : "2026-04-27 18:14:54.096",
		"updatedAt" : "2026-04-27 18:18:24.680",
		"isLocked" : 0,
		"settlementSnapshot" : "{\"paymentDate\": \"2026-04-27T00:00:00.000Z\", \"totalSettled\": 19998, \"settledChallans\": [{\"challanId\": 233, \"amountSettled\": 3332, \"challanNumber\": \"130407\", \"settlementDate\": \"2026-04-27T00:00:00.000Z\"}, {\"challanId\": 234, \"amountSettled\": 16666, \"challanNumber\": \"951401\", \"settlementDate\": \"2026-04-27T00:00:00.000Z\"}]}"
	}
]
